Metadata-Version: 1.1
Name: anarion
Version: 0.0.2
Summary: Stock Analysis
Home-page: https://github.com/nabhat/anarion
Author: nabhat
Author-email: angman507@gmail.com
License: MIT
Keywords: anarion
Platform: UNKNOWN
Classifier: Development Status :: 5 - Production/Stable
Classifier: Operating System :: OS Independent
Classifier: License :: OSI Approved :: MIT License
Classifier: Programming Language :: Python :: 3
